{
    "format_version": "1.10.0",
    "animation_controllers": {
        "controller.animation.air": {
            "states": {
                "default": {
                    "transitions": [
                        {
                            "air": "(1.0)"
                        }
                    ],
                    "on_entry": [
                        "/function skill/break",
                        "/tp @s ~ 200 ~",
                        "/kill @s"
                    ]
                },
                "air": {
                    "on_entry": [
                        "/function skill/break",
                        "/tp @s ~ 200 ~",
                        "/kill @s"
                    ],
                    "transitions": [
                        {
                            "default": "(1.0)"
                        }
                    ]
                }
            }
        }
    }
}